genericsuite/__init__.py
genericsuite/chalicelib/__init__.py
genericsuite/chalicelib/endpoints/__init__.py
genericsuite/chalicelib/endpoints/menu_options.py
genericsuite/chalicelib/endpoints/storage_retrieval.py
genericsuite/chalicelib/endpoints/users.py
genericsuite/chalicelib/framework_abstraction.py
genericsuite/chalicelib/util/__init__.py
genericsuite/chalicelib/util/blueprint_one.py
genericsuite/chalicelib/util/create_app.py
genericsuite/chalicelib/util/generic_endpoint_builder.py
genericsuite/config/__init__.py
genericsuite/config/config.py
genericsuite/config/config_from_db.py
genericsuite/config/config_secrets.py
genericsuite/config/logging.conf.yml
genericsuite/constants/__init__.py
genericsuite/constants/const_tables.py
genericsuite/fastapilib/__init__.py
genericsuite/fastapilib/endpoints/__init__.py
genericsuite/fastapilib/endpoints/menu_options.py
genericsuite/fastapilib/endpoints/storage_retrieval.py
genericsuite/fastapilib/endpoints/users.py
genericsuite/fastapilib/framework_abstraction.py
genericsuite/fastapilib/util/__init__.py
genericsuite/fastapilib/util/blueprint_one.py
genericsuite/fastapilib/util/create_app.py
genericsuite/fastapilib/util/dependencies.py
genericsuite/fastapilib/util/generic_endpoint_builder.py
genericsuite/fastapilib/util/parse_multipart.py
genericsuite/flasklib/__init__.py
genericsuite/flasklib/endpoints/__init__.py
genericsuite/flasklib/endpoints/menu_options.py
genericsuite/flasklib/endpoints/storage_retrieval.py
genericsuite/flasklib/endpoints/users.py
genericsuite/flasklib/framework_abstraction.py
genericsuite/flasklib/util/__init__.py
genericsuite/flasklib/util/blueprint_one.py
genericsuite/flasklib/util/create_app.py
genericsuite/flasklib/util/generic_endpoint_builder.py
genericsuite/flasklib/util/jwt.py
genericsuite/flasklib/util/parse_multipart.py
genericsuite/mcplib/__init__.py
genericsuite/mcplib/endpoints/__init__.py
genericsuite/mcplib/endpoints/users.py
genericsuite/mcplib/framework_abstraction.py
genericsuite-0.2.0.dist-info/METADATA
genericsuite-0.2.0.dist-info/WHEEL
genericsuite-0.2.0.dist-info/licenses/LICENSE
genericsuite-0.2.0.dist-info/RECORD
