Metadata-Version: 2.4
Name: genericsuite
Version: 0.2.0
Summary: The GenericSuite for Python (backend version)
License: ISC
License-File: LICENSE
Author: Carlos J. Ramirez
Author-email: info@genericsuite.com
Requires-Python: >=3.10,<4.0
Classifier: Development Status :: 3 - Alpha
Classifier: Environment :: Console
Classifier: Intended Audience :: Developers
Classifier: Programming Language :: Python :: 3
Classifier: Programming Language :: Python :: 3.9
Classifier: Programming Language :: Python :: 3.10
Classifier: Programming Language :: Python :: 3.11
Classifier: Programming Language :: Python :: 3.12
Classifier: Operating System :: OS Independent
Classifier: Topic :: Software Development
Requires-Dist: boto3 (>=1.40.19)
Requires-Dist: cryptography (>=44.0.1,<45.0.0)
Requires-Dist: dnspython (>=2.6.1)
Requires-Dist: fastmcp (>=2.13.0,<3.0.0)
Requires-Dist: marshmallow (>=3.19.0,<4.0.0)
Requires-Dist: mcp (>=1.21.0)
Requires-Dist: pydantic (>=2.9.2,<3.0.0)
Requires-Dist: pyjwt (>=2.8.0,<3.0.0)
Requires-Dist: pymongo (>=4.6.0,<5.0.0)
Requires-Dist: python-dateutil (>=2.8.2,<3.0.0)
Requires-Dist: requests (>=2.32.4,<3.0.0)
Requires-Dist: urllib3 (>=2.5.0,<3.0.0)
Requires-Dist: werkzeug (>=3.0.6,<4.0.0)
Requires-Dist: wheel (>=0.41.3,<0.42.0)
Project-URL: Homepage, https://genericsuite.carlosjramirez.com/Backend-Development/GenericSuite-Core/
Project-URL: Issues, https://github.com/tomkat-cr/genericsuite-be/issues
